StarLighting/__init__.py
StarLighting/excel.py
StarLighting/mail.py
StarLighting/sl_csv.py
StarLighting/sl_excel.py
star_lighting-0.5.dist-info/DESCRIPTION.rst
star_lighting-0.5.dist-info/METADATA
star_lighting-0.5.dist-info/RECORD
star_lighting-0.5.dist-info/WHEEL
star_lighting-0.5.dist-info/metadata.json
star_lighting-0.5.dist-info/top_level.txt
