Metadata-Version: 2.0
Name: star-lighting
Version: 0.5
Summary: simplely use python
Home-page: UNKNOWN
Author: duxinn
Author-email: xiamin_1990@yahoo.com
License: UNKNOWN
Platform: UNKNOWN
Requires-Dist: numpy
Requires-Dist: openpyxl
Requires-Dist: xlrd
Requires-Dist: xlwt
